docassemble.law-0.5.9-py3.7-nspkg.pth
docassemble/law/__init__.py
docassemble/law/data/questions/demo.yml
docassemble/law/data/questions/icop.yml
docassemble/law/data/questions/ngcw.yml
docassemble/law/data/questions/ngcw2.yml
docassemble/law/data/templates/fee_waiver.pdf
docassemble/law/data/templates/gender_change.pdf
docassemble/law/data/templates/name_and_gender_change.pdf
docassemble/law/data/templates/name_change.pdf
docassemble.law-0.5.9.dist-info/METADATA
docassemble.law-0.5.9.dist-info/WHEEL
docassemble.law-0.5.9.dist-info/namespace_packages.txt
docassemble.law-0.5.9.dist-info/top_level.txt
docassemble.law-0.5.9.dist-info/RECORD
