Metadata-Version: 2.1
Name: docassemble.law
Version: 0.5.9
Summary: Legal Automation Workshop
Home-page: https://github.com/AriChivukula/docassemble.law/
Author: Ari Chivukula
Author-email: ari.c@berkeley.edu
License: MIT
Platform: UNKNOWN
